LICENSE
README.md
qcd.py
requirements.txt
setup.py
qcd.egg-info/PKG-INFO
qcd.egg-info/SOURCES.txt
qcd.egg-info/dependency_links.txt
qcd.egg-info/not-zip-safe
qcd.egg-info/top_level.txt