Metadata-Version: 1.1
Name: qcd
Version: 0.0.1
Summary: QCD generator.
Home-page: https://github.com/riga
Author: Marcel Rieger
Author-email: python-qcd@googlegroups.com
License: MIT
Keywords: qcd,multijet,neural networks,generative,adversarial
Platform: UNKNOWN
Classifier: Programming Language :: Python
Classifier: Programming Language :: Python :: 2
Classifier: Programming Language :: Python :: 3
Classifier: Development Status :: 4 - Beta
Classifier: Operating System :: OS Independent
Classifier: License :: OSI Approved :: MIT License
Classifier: Intended Audience :: Developers
Classifier: Intended Audience :: Science/Research
Classifier: Intended Audience :: Information Technology
